atsas_pipelines/__init__.py
atsas_pipelines/_version.py
atsas_pipelines/cli.py
atsas_pipelines/dask.py
atsas_pipelines/run.py
atsas_pipelines/utils.py
atsas_pipelines/tests/__init__.py
atsas_pipelines/tests/conftest.py
atsas_pipelines/tests/test_utils.py
atsas_pipelines-0.1.0.dist-info/AUTHORS.rst
atsas_pipelines-0.1.0.dist-info/LICENSE
atsas_pipelines-0.1.0.dist-info/METADATA
atsas_pipelines-0.1.0.dist-info/WHEEL
atsas_pipelines-0.1.0.dist-info/entry_points.txt
atsas_pipelines-0.1.0.dist-info/top_level.txt
atsas_pipelines-0.1.0.dist-info/RECORD
